{
    "usuarios": [
        {
            "id": "0",
            "area": "Ventas",
            "usuario": "gglock",
            "clave": "123456",
            "nombre": "German",
            "apellido": "Glock",
            "telefono": "45881211",
            "email": "german_glock@sisdam.com"
        },
        {
            "id": "1",
            "area": "Servicios",
            "usuario": "gglock",
            "clave": "123456",
            "nombre": "German",
            "apellido": "Glock",
            "telefono": "45881211",
            "email": "german_glock@sisdam.com"
        },
        {
            "id": "3",
            "area": "Servicios",
            "usuario": "ggloc11111k",
            "clave": "123456",
            "nombre": "German",
            "apellido": "Glock",
            "telefono": "45881211",
            "email": "german_glock@sisdam.com"
        }        
    ]
}